{
  "balanceUsd": "$0.00",
  "exposureUsd": "$7.81",
  "positionsCount": 6,
  "totalPnlUsd": "-$47.77",
  "lastTrades": [
    {
      "side": "BUY YES",
      "symbol": "Will Elon Musk post 180-199 tweets from April 3 to April 10, 2026?",
      "price": "$0.016",
      "size": "22.50"
    },
    {
      "side": "BUY NO",
      "symbol": "Games Total: O/U 2.5",
      "price": "$0.190",
      "size": "0.00"
    },
    {
      "side": "BUY YES",
      "symbol": "Bitcoin Up or Down - April 7, 3:30PM-3:45PM ET",
      "price": "$0.100",
      "size": "17.86"
    },
    {
      "side": "BUY YES",
      "symbol": "Ethereum Up or Down - April 7, 3:30PM-3:45PM ET",
      "price": "$0.130",
      "size": "10.42"
    },
    {
      "side": "BUY YES",
      "symbol": "Will Elon Musk post 40-64 tweets from April 6 to April 8, 2026?",
      "price": "$0.103",
      "size": "19.41"
    }
  ],
  "updatedAt": "4/7/2026, 4:06:38 PM ET"
}